[
  {
    "header": "Ach. wt(Kg)",
    "placeholder": "{Ach. wt(Kg)}",
    "mapping": "records.ach_wt_kg"
  },
  {
    "header": "Error %",
    "placeholder": "{Error %}",
    "mapping": "records.error_pct"
  },
  {
    "header": "Error(Kg)",
    "placeholder": "{Error(Kg)}",
    "mapping": "records.error_kg"
  },
  {
    "header": "From Date",
    "placeholder": "{From Date}",
    "mapping": "UNRESOLVED"
  },
  {
    "header": "Location",
    "placeholder": "{Location}",
    "mapping": "INPUT_SAMPLE"
  },
  {
    "header": "Material name",
    "placeholder": "{Material name}",
    "mapping": "records.material_name"
  },
  {
    "header": "Plant name",
    "placeholder": "{Plant name}",
    "mapping": "INPUT_SAMPLE"
  },
  {
    "header": "Print Date",
    "placeholder": "{Print Date}",
    "mapping": "records.report_date"
  },
  {
    "header": "Recipe code",
    "placeholder": "{Recipe code}",
    "mapping": "INPUT_SAMPLE"
  },
  {
    "header": "Set. wt(Kg)",
    "placeholder": "{Set. wt(Kg)}",
    "mapping": "records.set_wt_kg"
  },
  {
    "header": "Sl. No.",
    "placeholder": "{Sl. No.}",
    "mapping": "records.sl_no"
  },
  {
    "header": "Total",
    "placeholder": "{Total}",
    "mapping": "UNRESOLVED"
  }
]